odoo/addons/product_simple_seasonality/README.rst
odoo/addons/product_simple_seasonality/__init__.py
odoo/addons/product_simple_seasonality/__manifest__.py
odoo/addons/product_simple_seasonality/i18n/it.po
odoo/addons/product_simple_seasonality/i18n/product_simple_seasonality.pot
odoo/addons/product_simple_seasonality/models/__init__.py
odoo/addons/product_simple_seasonality/models/product_packaging.py
odoo/addons/product_simple_seasonality/models/product_template.py
odoo/addons/product_simple_seasonality/models/seasonality.py
odoo/addons/product_simple_seasonality/readme/CONFIGURE.md
odoo/addons/product_simple_seasonality/readme/CONTRIBUTORS.md
odoo/addons/product_simple_seasonality/readme/DESCRIPTION.md
odoo/addons/product_simple_seasonality/readme/ROADMAP.md
odoo/addons/product_simple_seasonality/security/seasonality.xml
odoo/addons/product_simple_seasonality/static/description/icon.png
odoo/addons/product_simple_seasonality/static/description/index.html
odoo/addons/product_simple_seasonality/static/description/product.png
odoo/addons/product_simple_seasonality/static/description/seasonality.png
odoo/addons/product_simple_seasonality/views/product_packaging.xml
odoo/addons/product_simple_seasonality/views/product_template.xml
odoo/addons/product_simple_seasonality/views/seasonality.xml
odoo_addon_product_simple_seasonality-16.0.1.0.0.4.dist-info/METADATA
odoo_addon_product_simple_seasonality-16.0.1.0.0.4.dist-info/WHEEL
odoo_addon_product_simple_seasonality-16.0.1.0.0.4.dist-info/top_level.txt
odoo_addon_product_simple_seasonality-16.0.1.0.0.4.dist-info/RECORD
